ahab.py
ahabclient-0.0.14.dist-info/METADATA
ahabclient-0.0.14.dist-info/RECORD
ahabclient-0.0.14.dist-info/WHEEL
ahabclient-0.0.14.dist-info/entry_points.txt
ahabclient-0.0.14.dist-info/top_level.txt
